{
    "PLTR": {
        "current_price": 145.42,
        "50_week_moving_average": 160.23,
        "50_week_moving_average_slope": -148.5956,
        "50_week_ema": 11.25,
        "200_week_moving_average": 54.26,
        "200_week_moving_average_slope": -152.363,
        "200_week_ema": 8.83,
        "fibonacci_levels": {
            "0.0%": 207.52,
            "23.6%": 159.92,
            "38.2%": 130.48,
            "50.0%": 106.68,
            "61.8%": 82.88,
            "100.0%": 5.84,
            "123.6%": -41.76,
            "138.2%": -71.2,
            "161.8%": -118.8,
            "200.0%": -195.84,
            "261.8%": -320.48
        },
        "rsi": 42.26,
        "macd": {
            "macd_line": -0.93,
            "signal_line": -0.09,
            "histogram": -0.84
        },
        "bollinger_bands": {
            "middle_band": 12.49,
            "upper_band": 14.73,
            "lower_band": 10.25
        },
        "isInteresting": true,
        "timestamp": "2026-03-02T19:39:09.915455+00:00"
    }
}